stopes/__init__.py
stopes/hub.py
stopes/core/__init__.py
stopes/core/cache.py
stopes/core/launcher.py
stopes/core/stopes_module.py
stopes/core/utils.py
stopes/core/jobs_registry/__init__.py
stopes/core/jobs_registry/registry.py
stopes/core/jobs_registry/stopes_job.py
stopes/core/jobs_registry/submitit_slurm_job.py
stopes/core/tests/__init__.py
stopes/core/tests/hello_world.py
stopes/core/tests/test_headers.py
stopes/core/tests/test_launcher.py
stopes/core/tests/test_modules.py
stopes/core/tests/test_registry.py
stopes/core/tests/test_utils.py
stopes/core/tests/conf/employee.yaml
stopes/core/tests/conf/employment/department.yaml
stopes/core/tests/conf/employment/projects.yaml
stopes/eval/README.md
stopes/eval/__init__.py
stopes/eval/alti/LICENSE.md
stopes/eval/alti/README.md
stopes/eval/alti/__init__.py
stopes/eval/alti/alignment/__init__.py
stopes/eval/alti/alignment/align.py
stopes/eval/alti/alti_metrics/alti_metrics_utils.py
stopes/eval/alti/alti_metrics/file_utils.py
stopes/eval/alti/alti_metrics/nllb_alti_detector.py
stopes/eval/alti/wrappers/__init__.py
stopes/eval/alti/wrappers/multilingual_transformer_wrapper.py
stopes/eval/alti/wrappers/transformer_wrapper.py
stopes/eval/alti/wrappers/utils.py
stopes/eval/auto_pcp/README.md
stopes/eval/auto_pcp/audio_comparator.py
stopes/eval/auto_pcp/comparator_training.py
stopes/eval/auto_pcp/contrastive_training.py
stopes/eval/auto_pcp/prosody_probing.py
stopes/eval/blaser/README.md
stopes/eval/blaser/__init__.py
stopes/eval/blaser/blaser2.py
stopes/eval/blaser/model.py
stopes/eval/blaser/score.py
stopes/eval/blaser/train.py
stopes/eval/blaser/utils.py
stopes/eval/blaser/conf/score.yaml
stopes/eval/blaser/conf/train.yaml
stopes/eval/local_prosody/README.md
stopes/eval/local_prosody/__init__.py
stopes/eval/local_prosody/annotate_utterances.py
stopes/eval/local_prosody/compare_utterances.py
stopes/eval/local_prosody/ctc_forced_aligner.py
stopes/eval/local_prosody/emphasis_detection.py
stopes-2.2.1.dist-info/LICENSE.md
stopes-2.2.1.dist-info/WHEEL
stopes-2.2.1.dist-info/METADATA
stopes-2.2.1.dist-info/RECORD
