Metadata-Version: 2.3
Name: stopes
Version: 2.2.1
Summary: Large-Scale Translation Data Mining.
Author: Facebook AI Research
Requires-Python: >=3.9
Classifier: License :: OSI Approved :: MIT License
Classifier: Topic :: Scientific/Engineering
Classifier: Development Status :: 4 - Beta
Requires-Dist: hydra-core>=1.2.0
Requires-Dist: joblib
Requires-Dist: submitit>=1.4.5
Requires-Dist: tqdm
Requires-Dist: posix_ipc
Requires-Dist: pyarrow>=16.1.0
Requires-Dist: einops ; extra == "alti"
Requires-Dist: numpy ; extra == "alti"
Requires-Dist: omegaconf ; extra == "alti"
Requires-Dist: torch ; extra == "alti"
Requires-Dist: transformers ; extra == "auto-pcp"
Requires-Dist: pandas ; extra == "auto-pcp"
Requires-Dist: scipy ; extra == "auto-pcp"
Requires-Dist: scipy ; extra == "blaser"
Requires-Dist: numpy ; extra == "blaser"
Requires-Dist: torch ; extra == "blaser"
Requires-Dist: pytest>=4.3.0 ; extra == "dev"
Requires-Dist: pytest-asyncio>=0.15.0 ; extra == "dev"
Requires-Dist: pytest-cov>=2.6.1 ; extra == "dev"
Requires-Dist: coverage[toml]>=5.1 ; extra == "dev"
Requires-Dist: black==22.3.0 ; extra == "dev"
Requires-Dist: isort>=5.12.0 ; extra == "dev"
Requires-Dist: mypy>=1.1.1 ; extra == "dev"
Requires-Dist: types-emoji ; extra == "dev"
Requires-Dist: types-requests ; extra == "dev"
Requires-Dist: types-PyYAML ; extra == "dev"
Requires-Dist: pylint>=2.8.0 ; extra == "dev"
Requires-Dist: flit>=3.5.1 ; extra == "dev"
Requires-Dist: bs4 ; extra == "hmine"
Requires-Dist: func_argparse ; extra == "hmine"
Requires-Dist: nltk ; extra == "hmine"
Requires-Dist: pandas ; extra == "hmine"
Requires-Dist: scipy ; extra == "hmine"
Requires-Dist: scikit-learn ; extra == "hmine"
Requires-Dist: xxhash ; extra == "hmine"
Requires-Dist: transformers ; extra == "local-prosody"
Requires-Dist: pandas ; extra == "local-prosody"
Requires-Dist: syllables ; extra == "local-prosody"
Requires-Dist: phonemizer ; extra == "local-prosody"
Requires-Dist: ipapy ; extra == "local-prosody"
Requires-Dist: nltk ; extra == "local-prosody"
Requires-Dist: sacremoses ; extra == "local-prosody"
Requires-Dist: requests ; extra == "mining"
Requires-Dist: fairscale ; extra == "mining"
Requires-Dist: faiss-cpu ; extra == "mining"
Requires-Dist: sentencepiece ; extra == "mining"
Requires-Dist: numpy>=1.21 ; extra == "mining"
Requires-Dist: faiss-gpu ; extra == "mining-gpu"
Requires-Dist: xxhash ; extra == "mono"
Requires-Dist: fasttext ; extra == "mono"
Requires-Dist: sentence_splitter ; extra == "mono"
Requires-Dist: sacremoses ; extra == "mono"
Requires-Dist: sentencepiece ; extra == "mono"
Requires-Dist: indic-nlp-library ; extra == "mono"
Requires-Dist: emoji ; extra == "mono"
Requires-Dist: pythainlp==4.0.2 ; extra == "mono"
Requires-Dist: hasami ; extra == "mono"
Requires-Dist: botok ; extra == "mono"
Requires-Dist: khmer-nltk ; extra == "mono"
Requires-Dist: laonlp ; extra == "mono"
Requires-Dist: sonar-space==0.2.* ; extra == "sonar-mining"
Requires-Dist: fairseq2==0.2.* ; extra == "sonar-mining"
Requires-Dist: hanziconv ; extra == "speech"
Requires-Dist: inflect ; extra == "speech"
Requires-Dist: tnkeeh ; extra == "speech"
Requires-Dist: torchaudio ; extra == "speech"
Requires-Dist: num2words ; extra == "speech"
Requires-Dist: pandas ; extra == "speech"
Requires-Dist: unidecode ; extra == "speech"
Requires-Dist: transformers ; extra == "speech"
Requires-Dist: whisper ; extra == "speech"
Requires-Dist: encodec ; extra == "speech"
Requires-Dist: demucs ; extra == "speech"
Requires-Dist: librosa ; extra == "speech"
Requires-Dist: librosa ; extra == "video-alignment"
Requires-Dist: sentence_transformers ; extra == "video-alignment"
Requires-Dist: torchaudio ; extra == "video-alignment"
Requires-Dist: scipy ; extra == "video-alignment"
Requires-Dist: pandas ; extra == "video-alignment"
Requires-Dist: pyarrow>=16.1.0 ; extra == "video-alignment"
Requires-Dist: numba ; extra == "video-alignment"
Requires-Dist: transformers ; extra == "video-alignment"
Requires-Dist: openai-whisper==20230314 ; extra == "video-alignment"
Requires-Dist: fairseq2==0.2.* ; extra == "video-alignment"
Requires-Dist: sonar-space==0.2.* ; extra == "video-alignment"
Requires-Dist: s3prl ; extra == "vocal-style-sim"
Project-URL: Source, https://github.com/facebookresearch/stopes
Project-URL: Tracker, https://github.com/facebookresearch/stopes/issues
Provides-Extra: alti
Provides-Extra: auto-pcp
Provides-Extra: blaser
Provides-Extra: dev
Provides-Extra: hmine
Provides-Extra: local-prosody
Provides-Extra: mining
Provides-Extra: mining-gpu
Provides-Extra: mono
Provides-Extra: sonar-mining
Provides-Extra: speech
Provides-Extra: video-alignment
Provides-Extra: vocal-style-sim
